celery_sql_beat_reloader/__init__.py
celery_sql_beat_reloader/crontabtz.py
celery_sql_beat_reloader/db.py
celery_sql_beat_reloader/models.py
celery_sql_beat_reloader/reloader.py
celery_sql_beat_reloader-0.0.2.dist-info/LICENSE
celery_sql_beat_reloader-0.0.2.dist-info/METADATA
celery_sql_beat_reloader-0.0.2.dist-info/WHEEL
celery_sql_beat_reloader-0.0.2.dist-info/top_level.txt
celery_sql_beat_reloader-0.0.2.dist-info/RECORD
