Metadata-Version: 2.1
Name: celery-sql-beat-reloader
Version: 0.0.2
Summary: A Celery beat scheduler in SQL
Home-page: https://github.com/sir-wiggles/celery-sql-beat-reloader
Author: Jeff
Author-email: jeffmgreg@gmail.com
License: MIT
Keywords: celery beat scheduler sql
Platform: any
Classifier: Development Status :: 3 - Alpha
Classifier: Intended Audience :: Developers
Classifier: Topic :: Software Development :: Libraries
Classifier: License :: OSI Approved :: MIT License
Classifier: Programming Language :: Python :: 3
Classifier: Programming Language :: Python :: 3.7
License-File: LICENSE
Requires-Dist: celery (>=5.2)
Requires-Dist: sqlalchemy
